MANIFEST.in
README.md
setup.py
speakers/__init__.py
speakers/admin.py
speakers/app_registry.py
speakers/feeds.py
speakers/forms.py
speakers/managers.py
speakers/models.py
speakers/search_indexes.py
speakers/settings.json
speakers/signals.py
speakers/urls.py
speakers/views.py
speakers/migrations/0001_initial.py
speakers/migrations/0002_auto__chg_field_speaker_creator__chg_field_speaker_entity__chg_field_s.py
speakers/migrations/0003_auto__add_track__add_field_speaker_track_tmp.py
speakers/migrations/0004_populate_track_table_backup_track_field.py
speakers/migrations/0005_auto__del_field_speaker_track.py
speakers/migrations/0006_auto__add_field_speaker_track.py
speakers/migrations/0007_reassign_track_field.py
speakers/migrations/0008_auto__add_unique_track_name.py
speakers/migrations/0009_auto__del_field_speaker_track_tmp.py
speakers/migrations/__init__.py
speakers/static/css/speaker.css
speakers/static/images/speakers-default.jpg
speakers/templates/search/indexes/speakers/speaker_text.txt
speakers/templates/speakers/base.html
speakers/templates/speakers/options.html
speakers/templates/speakers/search-form.html
speakers/templates/speakers/search-result.html
speakers/templates/speakers/search.html
speakers/templates/speakers/view.html
speakers/templatetags/__init__.py
speakers/templatetags/speaker_tags.py
tendenci_speakers.egg-info/PKG-INFO
tendenci_speakers.egg-info/SOURCES.txt
tendenci_speakers.egg-info/dependency_links.txt
tendenci_speakers.egg-info/requires.txt
tendenci_speakers.egg-info/top_level.txt